kubectl_py-0.1.0.data/purelib/kubectl_py/kustomize.py
kubectl_py-0.1.0.data/scripts/kubectl
kubectl_py-0.1.0.dist-info/licenses/LICENSE
kubectl_py-0.1.0.dist-info/METADATA
kubectl_py-0.1.0.dist-info/WHEEL
kubectl_py-0.1.0.dist-info/entry_points.txt
kubectl_py-0.1.0.dist-info/top_level.txt
kubectl_py-0.1.0.dist-info/RECORD
