Metadata-Version: 2.4
Name: kubectl_py
Version: 0.1.0
Summary: Python wrapper around invoking kubectl (https://kubernetes.io/docs/reference/kubectl/)
Home-page: https://github.com/harryvince/kubectl-py
Author: Harry Vince
License: MIT
Classifier: Programming Language :: Python :: 3
Classifier: Programming Language :: Python :: 3 :: Only
Classifier: Programming Language :: Python :: Implementation :: CPython
Classifier: Programming Language :: Python :: Implementation :: PyPy
Requires-Python: >=3.9
License-File: LICENSE
Dynamic: license-file
